{
  "metadata": {
    "name": "phicons",
    "lastOpened": 1418773394855,
    "created": 1715772925778
  },
  "iconSets": [
    {
      "selection": [
        {
          "order": 57,
          "id": 2,
          "name": "rss_feed",
          "prevSize": 32,
          "code": 59648,
          "tempChar": "",
          "ligatures": "rss, feed, rss_feed"
        },
        {
          "order": 23,
          "id": 8,
          "name": "arrow_right",
          "prevSize": 32,
          "code": 59649,
          "tempChar": "",
          "ligatures": "arrow_right"
        },
        {
          "order": 13,
          "id": 3,
          "name": "info",
          "prevSize": 32,
          "code": 59651,
          "tempChar": "",
          "ligatures": "info"
        },
        {
          "order": 15,
          "id": 1,
          "name": "warning",
          "prevSize": 32,
          "code": 59652,
          "tempChar": "",
          "ligatures": "warning"
        },
        {
          "order": 19,
          "id": 7,
          "name": "error",
          "prevSize": 32,
          "code": 59653,
          "tempChar": "",
          "ligatures": "error, danger, attention"
        },
        {
          "order": 33,
          "id": 10,
          "name": "note",
          "prevSize": 32,
          "code": 59676,
          "tempChar": "",
          "ligatures": "note"
        },
        {
          "order": 32,
          "id": 9,
          "name": "lightbulb",
          "prevSize": 32,
          "code": 59677,
          "tempChar": "",
          "ligatures": "lightbulb, idea"
        },
        {
          "order": 42,
          "id": 33,
          "name": "bolt",
          "prevSize": 32,
          "code": 59650,
          "tempChar": "",
          "ligatures": "bolt"
        },
        {
          "order": 45,
          "id": 30,
          "name": "search",
          "prevSize": 32,
          "code": 59658,
          "tempChar": "",
          "ligatures": "search"
        },
        {
          "order": 39,
          "id": 16,
          "name": "person",
          "prevSize": 32,
          "code": 59672,
          "tempChar": "",
          "ligatures": "person"
        },
        {
          "order": 37,
          "id": 14,
          "name": "fingerprint",
          "prevSize": 32,
          "code": 59655,
          "tempChar": "",
          "ligatures": "fingerprint"
        },
        {
          "order": 36,
          "id": 13,
          "name": "encrypted",
          "prevSize": 32,
          "code": 59674,
          "tempChar": "",
          "ligatures": "encrypted"
        },
        {
          "order": 48,
          "id": 27,
          "name": "lock",
          "prevSize": 32,
          "code": 59661,
          "tempChar": "",
          "ligatures": "lock, locked"
        },
        {
          "order": 34,
          "id": 11,
          "name": "email",
          "prevSize": 32,
          "code": 59654,
          "tempChar": "",
          "ligatures": "email, at"
        },
        {
          "order": 35,
          "id": 12,
          "name": "tag",
          "prevSize": 32,
          "code": 59675,
          "tempChar": "",
          "ligatures": "tag, hashtag, irc"
        },
        {
          "order": 43,
          "id": 32,
          "name": "thumbs_down",
          "prevSize": 32,
          "code": 59656,
          "tempChar": "",
          "ligatures": "thumbs_down"
        },
        {
          "order": 44,
          "id": 31,
          "name": "thumbs_up",
          "prevSize": 32,
          "code": 59657,
          "tempChar": "",
          "ligatures": "thumbs_up"
        },
        {
          "order": 46,
          "id": 29,
          "name": "code",
          "prevSize": 32,
          "code": 59659,
          "tempChar": "",
          "ligatures": "code"
        },
        {
          "order": 49,
          "id": 26,
          "name": "globe",
          "prevSize": 32,
          "code": 59662,
          "tempChar": "",
          "ligatures": "globe, world, internet"
        },
        {
          "order": 38,
          "id": 15,
          "name": "heart",
          "prevSize": 32,
          "code": 59673,
          "tempChar": "",
          "ligatures": "heart"
        },
        {
          "order": 51,
          "id": 24,
          "name": "heart_broken",
          "prevSize": 32,
          "code": 59664,
          "tempChar": "",
          "ligatures": "heart_broken"
        },
        {
          "order": 41,
          "id": 18,
          "name": "star",
          "prevSize": 32,
          "code": 59670,
          "tempChar": "",
          "ligatures": "star"
        },
        {
          "order": 54,
          "id": 21,
          "name": "rocket",
          "prevSize": 32,
          "code": 59667,
          "tempChar": "",
          "ligatures": "rocket"
        },
        {
          "order": 47,
          "id": 28,
          "name": "terminal",
          "prevSize": 32,
          "code": 59660,
          "tempChar": "",
          "ligatures": "terminal"
        },
        {
          "order": 52,
          "id": 23,
          "name": "acute",
          "prevSize": 32,
          "code": 59665,
          "tempChar": "",
          "ligatures": "acute, timely"
        },
        {
          "order": 50,
          "id": 25,
          "name": "history",
          "prevSize": 32,
          "code": 59663,
          "tempChar": "",
          "ligatures": "history"
        },
        {
          "order": 53,
          "id": 22,
          "name": "cycle",
          "prevSize": 32,
          "code": 59666,
          "tempChar": "",
          "ligatures": "cycle"
        },
        {
          "order": 55,
          "id": 20,
          "name": "delete",
          "prevSize": 32,
          "code": 59668,
          "tempChar": "",
          "ligatures": "delete, trash"
        },
        {
          "order": 40,
          "id": 17,
          "name": "close",
          "prevSize": 32,
          "code": 59671,
          "tempChar": "",
          "ligatures": "close, cross"
        }
      ],
      "id": 3,
      "metadata": {
        "name": "Google Material Symbols",
        "importSize": {
          "width": 40,
          "height": 40
        },
        "license": "Apache License Version 2.0",
        "licenseURL": "https://www.apache.org/licenses/LICENSE-2.0",
        "url": "https://fonts.google.com/icons"
      },
      "height": 1024,
      "prevSize": 32,
      "icons": [
        {
          "id": 2,
          "paths": [
            "M209.781 896q-33.781 0-57.781-24t-24-57.781q0-33.771 24-57.771t57.781-24q33.771 0 57.771 24t24 57.771q0 33.781-24 57.781t-57.771 24zM800 896q-23.467 0-38.581-16.715-15.104-16.704-17.6-40.171-10.304-112-57.067-208.896-46.752-96.885-121.419-171.552t-171.552-121.419q-96.896-46.763-208.896-57.067-23.467-2.496-40.171-17.6-16.715-15.115-16.715-38.581t17.067-38.219q17.067-14.763 40.181-12.629 134.037 10.315 250.133 65.248 116.085 54.933 205.685 144.533t144.533 205.685q54.933 116.096 65.248 250.133 2.133 23.115-12.629 40.181-14.752 17.067-38.219 17.067zM531.2 896q-22.4 0-38.4-15.819-16-15.829-19.2-38.933-8.885-57.963-33.952-107.563t-64.181-88.704q-39.115-39.115-87.648-65.248t-105.771-35.019q-22.4-3.915-38.229-19.563-15.819-15.637-15.819-38.037 0-22.763 16-38.048t37.685-12.448q79.296 9.248 147.733 43.915 68.448 34.667 121.781 88.715 53.333 54.037 87.285 123.904 33.963 69.867 43.2 149.163 2.848 22.4-12.437 38.037-15.296 15.648-38.048 15.648z"
          ],
          "attrs": [
            {}
          ],
          "isMulticolor": false,
          "isMulticolor2": false,
          "grid": 32,
          "tags": [
            "rss",
            "feed"
          ]
        },
        {
          "id": 8,
          "paths": [
            "M556.085 511.285l-181.333-181.333q-10.304-10.304-9.952-24.885t10.667-24.885q10.315-10.315 25.248-10.315t25.237 10.315l206.229 206.219q5.685 5.685 8 11.733 2.304 6.048 2.304 13.152 0 7.115-2.304 13.163-2.315 6.037-8 11.733l-206.933 206.933q-10.315 10.304-24.896 9.952-14.571-0.352-24.885-10.667t-10.315-25.248 10.315-25.237l180.619-180.629z"
          ],
          "attrs": [
            {}
          ],
          "isMulticolor": false,
          "isMulticolor2": false,
          "grid": 32,
          "tags": [
            "arrow",
            "right",
            "chevron"
          ]
        },
        {
          "id": 3,
          "paths": [
            "M514.261 725.333q15.157 0 25.291-10.219 10.133-10.229 10.133-25.333v-184.896q0-15.104-10.251-25.333-10.261-10.219-25.429-10.219-15.157 0-25.291 10.219-10.133 10.229-10.133 25.333v184.896q0 15.104 10.251 25.333 10.261 10.219 25.429 10.219zM511.989 388.267q16.011 0 26.859-10.635 10.837-10.624 10.837-26.347 0-16.32-10.827-27.36-10.837-11.040-26.848-11.040t-26.859 11.040q-10.837 11.040-10.837 27.36 0 15.723 10.827 26.347 10.837 10.635 26.848 10.635zM512.192 938.667q-88.352 0-166.048-33.6t-135.659-91.552q-57.952-57.963-91.552-135.712t-33.6-166.155 33.6-166.165q33.6-77.749 91.552-135.349 57.963-57.6 135.712-91.2t166.155-33.6 166.165 33.6q77.749 33.6 135.349 91.2t91.2 135.467 33.6 166.208q0 88.352-33.6 166.048t-91.2 135.52-135.467 91.563q-77.867 33.728-166.208 33.728zM512.352 867.552q148.267 0 251.733-103.819t103.467-252.085-103.328-251.733q-103.339-103.467-252.224-103.467-147.915 0-251.733 103.328-103.819 103.339-103.819 252.224 0 147.915 103.819 251.733t252.085 103.819z"
          ],
          "attrs": [
            {}
          ],
          "isMulticolor": false,
          "isMulticolor2": false,
          "grid": 32,
          "tags": [
            "info",
            "circle"
          ]
        },
        {
          "id": 1,
          "paths": [
            "M104.181 896q-10.315 0-18.251-4.885-7.925-4.896-12.331-12.896-4.736-7.893-5.216-17.099-0.469-9.205 5.216-18.453l407.467-704q5.685-9.248 13.685-13.515t17.248-4.267 17.248 4.267 13.685 13.515l407.467 704q5.685 9.248 5.216 18.453-0.48 9.205-5.216 17.099-4.405 8-12.331 12.896-7.936 4.885-18.251 4.885h-815.637zM165.685 824.885h692.629l-346.315-597.333-346.315 597.333zM514.965 770.133q15.168 0 25.301-10.261 10.133-10.251 10.133-25.419t-10.261-25.301q-10.251-10.133-25.419-10.133t-25.301 10.261-10.133 25.419q0 15.168 10.261 25.301t25.419 10.133zM514.965 648.533q15.168 0 25.301-10.219 10.133-10.229 10.133-25.333v-159.296q0-15.104-10.261-25.333-10.251-10.219-25.419-10.219t-25.301 10.219q-10.133 10.229-10.133 25.333v159.296q0 15.104 10.261 25.333 10.261 10.219 25.419 10.219z"
          ],
          "attrs": [
            {}
          ],
          "isMulticolor": false,
          "isMulticolor2": false,
          "grid": 32,
          "tags": [
            "warning",
            "triangle"
          ]
        },
        {
          "id": 7,
          "paths": [
            "M511.989 725.333q16.011 0 26.859-10.827 10.837-10.837 10.837-26.848t-10.827-26.859q-10.837-10.848-26.848-10.848t-26.859 10.837q-10.837 10.827-10.837 26.848 0 16.011 10.827 26.848 10.837 10.848 26.848 10.848zM514.261 559.648q15.157 0 25.291-10.229 10.133-10.219 10.133-25.333v-194.133q0-15.104-10.251-25.333-10.261-10.219-25.429-10.219-15.157 0-25.291 10.219-10.133 10.229-10.133 25.333v194.133q0 15.115 10.251 25.333 10.261 10.229 25.429 10.229zM512.192 938.667q-88.352 0-166.048-33.6t-135.659-91.552q-57.952-57.963-91.552-135.712t-33.6-166.155 33.6-166.165q33.6-77.749 91.552-135.349 57.963-57.6 135.712-91.2t166.155-33.6 166.165 33.6q77.749 33.6 135.349 91.2t91.2 135.467 33.6 166.208q0 88.352-33.6 166.048t-91.2 135.52-135.467 91.563q-77.867 33.728-166.208 33.728zM512.352 867.552q148.267 0 251.733-103.819t103.467-252.085-103.328-251.733q-103.339-103.467-252.224-103.467-147.915 0-251.733 103.328-103.819 103.339-103.819 252.224 0 147.915 103.819 251.733t252.085 103.819z"
          ],
          "attrs": [
            {}
          ],
          "isMulticolor": false,
          "isMulticolor2": false,
          "grid": 32,
          "tags": [
            "error",
            "circle",
            "attention"
          ]
        },
        {
          "id": 10,
          "paths": [
            "M532.267 737.781l377.952-377.248-76.085-75.381-377.248 377.248 75.381 75.381zM113.781 651.733q0 32.352 23.467 51.552t73.952 25.963q14.219 2.133 22.933 12.971 8.715 10.848 7.648 25.067-1.067 15.296-11.381 24.896t-24.533 7.467q-80.715-11.381-121.952-48.181-41.248-36.8-41.248-99.733 0-65.781 55.285-107.2 55.296-41.419 153.781-49.952 45.152-3.915 67.381-15.829 22.219-11.904 22.219-32.885 0-26.315-23.467-41.419-23.467-15.115-76.8-23.296-14.933-2.133-23.648-13.152-8.704-11.019-7.285-25.952 1.419-15.296 12.8-24.363t25.6-6.933q82.133 12.8 123.019 46.048 40.896 33.248 40.896 89.067 0 51.552-40.363 82.848-40.352 31.285-114.667 36.971-71.819 5.333-107.733 26.848-35.904 21.515-35.904 59.2zM552.533 818.133l-176-176 418.848-418.133q17.067-17.067 39.285-16.715 22.219 0.363 39.285 16.715l97.429 96.715q17.067 17.067 17.067 39.637 0 22.581-17.067 39.648l-418.848 418.133zM382.933 853.333q-18.133 4.267-32-9.6t-9.6-32l35.2-169.6 176 176-169.6 35.2z"
          ],
          "attrs": [
            {}
          ],
          "isMulticolor": false,
          "isMulticolor2": false,
          "grid": 32,
          "tags": [
            "note",
            "stylus",
            "draw"
          ]
        },
        {
          "id": 9,
          "paths": [
            "M512 938.667q-35.915 0-60.981-25.067t-25.067-60.981h172.096q0 35.915-25.067 60.981t-60.981 25.067zM375.467 794.315q-15.115 0-25.333-10.261t-10.219-25.419q0-15.168 10.219-25.301t25.333-10.133h273.067q15.115 0 25.333 10.261 10.219 10.251 10.219 25.419t-10.219 25.301-25.333 10.133h-273.067zM347.019 665.6q-71.467-45.152-113.237-115.552-41.781-70.4-41.781-156.8 0-131.2 94.4-225.6t225.6-94.4 225.6 94.4 94.4 225.6q0 86.4-41.419 156.8-41.429 70.4-113.6 115.552h-329.963zM371.2 594.485h282.069q50.379-34.133 78.997-87.2t28.619-114.037q0-103.115-72.885-176-72.885-72.896-176-72.896t-176 72.896q-72.885 72.885-72.885 176 0 60.971 28.619 114.037t79.467 87.2z"
          ],
          "attrs": [
            {}
          ],
          "isMulticolor": false,
          "isMulticolor2": false,
          "grid": 32,
          "tags": [
            "light",
            "bulb"
          ]
        },
        {
          "id": 33,
          "paths": [
            "M429.515 824.181l272-326.4h-184.896l35.915-284.096-245.685 355.2h158.933l-36.267 255.296zM384 640h-145.781q-21.237 0-31.413-19.019-10.187-19.029 2.613-36.8l346.667-499.915q9.248-12.8 23.467-17.6 14.229-4.8 28.8 0.885 14.581 5.696 22.4 18.965 7.829 13.28 5.696 28.331l-39.115 311.819h180.267q23.008 0 32.309 20.267 9.291 20.267-5.291 38.048l-380.8 456.533q-9.909 11.659-24.331 15.253-14.421 3.584-27.573-2.635-13.163-6.219-20.8-19.115-7.648-12.885-5.515-28l38.4-267.019z"
          ],
          "attrs": [
            {}
          ],
          "isMulticolor": false,
          "isMulticolor2": false,
          "grid": 32,
          "tags": [
            "bolt",
            "lightning"
          ]
        },
        {
          "id": 30,
          "paths": [
            "M403.915 676.267q-115.669 0-195.797-80.181-80.117-80.171-80.117-194.304t80.181-194.315q80.171-80.181 194.667-80.181 114.485 0 194.304 80.181 79.829 80.181 79.829 194.421 0 46.112-14.933 88.427-14.933 42.304-43.381 77.867l251.733 250.304q10.315 9.995 10.315 25.451 0 15.445-10.315 25.749-10.315 10.315-25.76 10.315t-25.44-10.315l-251.019-251.019q-32 27.019-74.283 42.315-42.283 15.285-89.984 15.285zM403.2 605.152q84.448 0 143.552-59.552 59.115-59.552 59.115-143.819t-59.115-143.829q-59.104-59.552-143.552-59.552-85.035 0-144.565 59.552-59.52 59.563-59.52 143.829t59.52 143.819q59.531 59.552 144.565 59.552z"
          ],
          "attrs": [
            {}
          ],
          "isMulticolor": false,
          "isMulticolor2": false,
          "grid": 32,
          "tags": [
            "search"
          ]
        },
        {
          "id": 16,
          "paths": [
            "M512 511.285q-70.4 0-116.981-46.571-46.571-46.581-46.571-116.981t46.571-116.981q46.581-46.571 116.981-46.571t116.981 46.571q46.571 46.581 46.571 116.981t-46.571 116.981q-46.581 46.571-116.981 46.571zM170.667 782.219v-35.552q0-39.115 19.733-68.448t51.381-44.619q69.685-32.352 136.171-48.533 66.496-16.181 134.048-16.181t133.685 16.533 135.765 48.32q32.576 15.381 52.224 44.597 19.659 29.216 19.659 68.331v35.552q0 29.333-20.885 50.229-20.896 20.885-50.229 20.885h-540.437q-29.333 0-50.229-20.885-20.885-20.896-20.885-50.229zM241.781 782.219h540.437v-35.552q0-15.285-8.704-28.8-8.715-13.515-21.867-20.267-64.715-31.648-121.963-44.619-57.237-12.981-117.685-12.981t-118.4 12.981q-57.952 12.971-121.952 44.619-13.163 6.752-21.515 20.267t-8.352 28.8v35.552zM512 440.181q39.467 0 65.952-26.496 26.496-26.485 26.496-65.952t-26.496-65.952q-26.485-26.496-65.952-26.496t-65.952 26.496q-26.496 26.485-26.496 65.952t26.496 65.952q26.485 26.496 65.952 26.496z"
          ],
          "attrs": [
            {}
          ],
          "isMulticolor": false,
          "isMulticolor2": false,
          "grid": 32,
          "tags": [
            "person"
          ]
        },
        {
          "id": 14,
          "paths": [
            "M513.067 192.352q114.485 0 215.819 48.896 101.333 48.885 168.533 140.619 4.629 6.752 3.381 11.381-1.248 4.619-5.515 8.533-4.267 3.904-10.304 3.733-6.048-0.181-11.029-6.581-61.504-86.048-157.333-132.085-95.819-46.048-203.552-46.048t-201.952 46.4q-94.229 46.4-156.8 131.733-4.981 6.752-10.315 7.819t-10.315-2.133q-5.333-3.2-5.867-9.067t3.029-11.552q66.133-91.381 166.933-141.515t215.285-50.133zM513.067 294.048q144.715 0 248.533 96t103.819 237.152q0 50.485-36.8 85.152t-89.067 34.667q-52.971 0-90.837-34.667t-37.867-85.152q0-39.467-28.981-65.952-28.981-26.496-68.8-26.496t-69.152 26.496q-29.333 26.485-29.333 65.952 0 108.448 65.237 180.981 65.248 72.533 164.448 101.685 7.467 2.485 9.6 7.115 2.133 4.619 0.715 10.304-1.429 6.048-5.696 9.248t-11.019 1.067q-110.219-27.733-180.981-110.048-70.752-82.304-70.752-200.352 0-51.2 37.333-86.048 37.333-34.837 89.6-34.837t89.6 34.837q37.333 34.848 37.333 86.048 0 38.752 29.867 65.248 29.867 26.485 69.685 26.485 39.115 0 67.915-26.485 28.8-26.496 28.8-65.248 0-128.715-95.285-215.819-95.296-87.115-227.563-87.115t-227.552 87.115q-95.285 87.104-95.285 215.467 0 25.6 5.504 65.771 5.515 40.181 24.363 92.096 2.485 6.752-0.181 11.019t-7.648 6.752q-5.685 2.496-11.552 0.533-5.867-1.952-8.352-8.352-14.581-40.885-22.229-82.667-7.637-41.781-7.637-84.8 0-139.019 104-236.085t246.219-97.067zM513.067 85.685q68.981 0 135.115 16.896 66.133 16.885 126.933 47.819 6.752 3.2 7.637 8.533 0.896 5.333-1.6 9.952-2.485 4.629-7.467 7.467-4.971 2.848-12.085-0.352-57.952-28.8-120.715-44.981-62.752-16.171-127.819-16.171-64.715 0-126.581 15.104-61.867 15.115-118.4 46.048-6.4 3.2-11.019 1.248-4.619-1.963-7.467-6.933-2.848-4.267-2.133-9.429 0.715-5.152 5.685-8.352 60.448-32.715 126.581-49.781t133.333-17.067zM513.067 400.352q98.485 0 169.6 65.6t71.115 161.248q0 6.752-3.733 10.485t-10.496 3.733q-6.4 0-10.667-3.733t-4.267-10.485q0-84.267-62.752-141.333t-148.8-57.067-147.733 57.067-61.685 141.333q0 89.248 30.933 152t91.371 125.685q4.981 4.981 4.629 10.315-0.363 5.333-4.629 9.6-3.552 3.552-9.6 4.619-6.037 1.067-11.019-4.619-62.219-64.715-96.533-134.581t-34.315-163.019q0-95.648 70.048-161.248t168.533-65.6zM512 612.267q6.752 0 10.485 4.267t3.733 10.667q0 84.267 61.515 138.667t142.581 54.4q7.819 0 19.552-1.067t25.248-3.2q6.752-1.419 11.2 1.952 4.437 3.381 5.867 8.715 1.419 5.685-1.429 9.952-2.837 4.267-9.237 5.696-19.2 5.333-33.6 5.867t-17.6 0.533q-94.229 0-163.381-62.933t-69.152-158.581q0-6.4 3.733-10.667t10.485-4.267z"
          ],
          "attrs": [
            {}
          ],
          "isMulticolor": false,
          "isMulticolor2": false,
          "grid": 32,
          "tags": [
            "fingerprint",
            "identity"
          ]
        },
        {
          "id": 13,
          "paths": [
            "M475.733 640h72.533q8 0 13.952-6.667 5.963-6.667 3.829-14.667l-22.4-127.648q21.664-10.059 34.112-29.184 12.459-19.125 12.459-42.283 0-32.267-22.997-55.243-22.987-22.976-55.285-22.976-32.288 0-55.221 22.976t-22.933 55.243q0 23.157 12.459 42.283 12.448 19.125 34.112 29.184l-22.4 127.648q-2.133 8 3.829 14.667 5.952 6.667 13.952 6.667zM512 934.4q-6.272 0-11.648-1.067t-10.752-3.2q-146.848-49.419-232.885-179.019-86.048-129.6-86.048-282.571v-206.496q0-22.581 12.885-40.651 12.896-18.069 33.333-26.197l270.229-100.981q12.8-4.619 24.885-4.619t24.885 4.619l270.229 100.981q20.437 8.128 33.333 26.197 12.885 18.069 12.885 40.651v206.496q0 152.971-86.048 282.571-86.037 129.6-232.885 179.019-5.376 2.133-10.752 3.2t-11.648 1.067zM512 864q118.752-38.752 194.485-148.981 75.733-110.219 75.733-246.4v-206.571l-270.219-101.696-270.219 101.696v206.571q0 136.181 75.733 246.4 75.733 110.229 194.485 148.981z"
          ],
          "attrs": [
            {}
          ],
          "isMulticolor": false,
          "isMulticolor2": false,
          "grid": 32,
          "tags": [
            "encrypted",
            "gpg"
          ]
        },
        {
          "id": 27,
          "paths": [
            "M241.781 938.667q-29.333 0-50.229-20.885-20.885-20.896-20.885-50.229v-450.837q0-29.333 20.885-50.229 20.896-20.885 50.229-20.885h64v-96.715q0-85.579 60.341-145.899t145.952-60.32 145.877 60.32 60.267 145.899v96.715h64q29.333 0 50.229 20.885 20.885 20.896 20.885 50.229v450.837q0 29.333-20.885 50.229-20.896 20.885-50.229 20.885h-540.437zM241.781 867.552h540.437v-450.837h-540.437v450.837zM512.117 725.333q34.368 0 58.731-24.021 24.352-24.021 24.352-57.76 0-33.067-24.48-58.837-24.469-25.781-58.837-25.781t-58.731 25.781q-24.352 25.771-24.352 59.2 0 33.419 24.48 57.419 24.469 24 58.837 24zM376.885 345.6h270.229v-96.715q0-56.288-39.381-95.701-39.392-39.403-95.648-39.403-56.267 0-95.733 39.403-39.467 39.413-39.467 95.701v96.715zM241.781 867.552v0z"
          ],
          "attrs": [
            {}
          ],
          "isMulticolor": false,
          "isMulticolor2": false,
          "grid": 32,
          "tags": [
            "lock",
            "secure"
          ]
        },
        {
          "id": 11,
          "paths": [
            "M512 938.667q-88.533 0-166.4-33.6t-135.467-91.2-91.2-135.467-33.6-166.4 33.6-166.4 91.2-135.467 135.467-91.2 166.4-33.6 166.4 33.6 135.467 91.2 91.2 135.467 33.6 166.4v58.315q0 60.8-42.379 102.933t-104.107 42.133q-38.101 0-71.851-17.781t-53.312-50.485q-28.8 34.485-69.568 51.371-40.768 16.896-85.451 16.896-84.693 0-144.395-59.2-59.691-59.2-59.691-144.192t59.691-144.885q59.701-59.904 144.395-59.904t144.395 59.904q59.691 59.904 59.691 144.896v58.315q0 31.008 22.048 52.48t53.685 21.472q31.648 0 53.696-21.472 22.037-21.472 22.037-52.48v-58.315q0-148.885-103.328-252.224-103.339-103.328-252.224-103.328t-252.224 103.328q-103.328 103.339-103.328 252.224t103.328 252.224q103.339 103.328 252.224 103.328h187.733q15.115 0 25.333 10.261t10.219 25.419q0 15.168-10.219 25.301t-25.333 10.133h-187.733zM512.043 644.267q55.424 0 94.176-38.581 38.763-38.571 38.763-93.685 0-56.181-38.805-94.933-38.795-38.752-94.219-38.752t-94.176 38.752q-38.763 38.752-38.763 94.933 0 55.115 38.805 93.685 38.795 38.581 94.219 38.581z"
          ],
          "attrs": [
            {}
          ],
          "isMulticolor": false,
          "isMulticolor2": false,
          "grid": 32,
          "tags": [
            "email",
            "mail",
            "at"
          ]
        },
        {
          "id": 12,
          "paths": [
            "M368.352 683.381l-36.619 144q-2.485 11.733-11.381 18.837-8.885 7.115-20.971 7.115-16.715 0-27.381-13.152-10.667-13.163-6.048-29.515l32-127.285h-124.8q-17.067 0-28.085-13.696-11.019-13.685-6.4-30.4 2.485-12.085 12.085-19.552t22.4-7.467h142.581l50.485-200.533h-124.8q-17.067 0-28.085-13.685-11.019-13.696-6.4-30.4 2.485-12.096 12.085-19.563t22.4-7.467h142.581l35.915-144q2.485-11.733 11.371-18.837 8.896-7.115 20.981-7.115 16.715 0 27.019 12.8 10.315 12.8 6.4 29.152l-31.285 128h201.248l35.904-144q2.496-11.733 11.381-18.837 8.885-7.115 20.981-7.115 16.704 0 27.019 12.8t6.4 29.152l-31.285 128h124.8q17.067 0 28.085 13.696 11.019 13.685 6.4 30.4-2.485 12.085-12.085 19.552t-22.4 7.467h-142.581l-50.485 200.533h124.8q17.067 0 28.085 13.685 11.019 13.696 6.4 30.4-2.485 12.096-12.085 19.563t-22.4 7.467h-142.581l-36.619 144q-2.496 11.733-11.381 18.837-8.885 7.115-20.981 7.115-16.704 0-27.371-13.152-10.667-13.163-6.048-29.515l32-127.285h-201.248zM386.133 612.267h201.248l50.485-200.533h-201.248l-50.485 200.533z"
          ],
          "attrs": [
            {}
          ],
          "isMulticolor": false,
          "isMulticolor2": false,
          "grid": 32,
          "tags": [
            "tag",
            "irc",
            "hash"
          ]
        },
        {
          "id": 32,
          "paths": [
            "M117.333 676.981q-28.448 0-49.781-21.333t-21.333-49.781v-86.645q0-7.573-0.352-15.755t2.485-15.648l132.267-306.485q9.515-22.219 31.712-37.781 22.197-15.552 46.517-15.552h472.171v548.981l-245.333 253.867q-14.997 15.285-35.509 17.952-20.501 2.667-39.509-8-18.848-10.667-28.085-29.515-9.248-18.837-4.416-39.104l43.52-195.2h-304.352zM659.915 647.115v-448h-410.315l-132.267 312.171v94.581h393.248l-56.896 255.285 206.229-214.037zM868.267 128q29.333 0 50.219 20.885 20.896 20.896 20.896 50.229v406.752q0 29.333-20.896 50.219-20.885 20.896-50.219 20.896h-137.248v-71.115h137.248v-406.752h-137.248v-71.115h137.248zM659.915 199.115v0z"
          ],
          "attrs": [
            {}
          ],
          "isMulticolor": false,
          "isMulticolor2": false,
          "grid": 32,
          "tags": [
            "thumb_down"
          ]
        },
        {
          "id": 31,
          "paths": [
            "M906.667 347.019q28.448 0 49.781 21.333t21.333 49.781v86.645q0 7.573 0.352 15.755t-2.485 15.648l-132.267 306.485q-9.515 22.219-31.712 37.781-22.197 15.552-46.517 15.552h-472.171v-548.981l245.333-253.867q14.997-15.285 35.509-17.952 20.501-2.667 39.509 8 18.848 10.667 28.085 29.515 9.248 18.837 4.416 39.104l-43.52 195.2h304.352zM364.085 376.885v448h410.315l132.267-312.171v-94.581h-393.248l56.896-255.285-206.229 214.037zM155.733 896q-29.333 0-50.219-20.885-20.896-20.896-20.896-50.229v-406.752q0-29.333 20.896-50.219 20.885-20.896 50.219-20.896h137.248v71.115h-137.248v406.752h137.248v71.115h-137.248zM364.085 824.885v0z"
          ],
          "attrs": [
            {}
          ],
          "isMulticolor": false,
          "isMulticolor2": false,
          "grid": 32,
          "tags": [
            "thumbs_up"
          ]
        },
        {
          "id": 29,
          "paths": [
            "M186.667 510.933l180.267 180.267q10.315 10.315 9.952 24.885-0.352 14.581-10.667 24.896-10.304 10.304-25.237 10.304t-25.248-10.304l-205.515-205.515q-5.685-5.685-8-11.733-2.304-6.048-2.304-13.152 0-7.115 2.304-13.163 2.315-6.037 8-11.733l207.648-207.637q10.667-10.667 25.419-10.667 14.763 0 25.429 10.667t10.667 25.419-10.667 25.419l-182.048 182.048zM837.333 510.219l-180.267-180.267q-10.315-10.304-9.952-24.885 0.352-14.581 10.667-24.885 10.304-10.315 25.237-10.315t25.248 10.315l205.515 205.504q5.685 5.696 8 11.733 2.304 6.048 2.304 13.163 0 7.104-2.304 13.152-2.315 6.048-8 11.733l-207.648 207.648q-10.667 10.667-24.885 10.133-14.229-0.533-24.896-11.2t-10.667-25.429q0-14.752 10.667-25.419l180.981-180.981z"
          ],
          "attrs": [
            {}
          ],
          "isMulticolor": false,
          "isMulticolor2": false,
          "grid": 32,
          "tags": [
            "code"
          ]
        },
        {
          "id": 26,
          "paths": [
            "M512.192 938.667q-88.352 0-166.048-33.6t-135.659-91.552q-57.952-57.963-91.552-135.712t-33.6-166.155 33.6-166.165q33.6-77.749 91.552-135.349 57.963-57.6 135.712-91.2t166.155-33.6 166.165 33.6q77.749 33.6 135.349 91.2t91.2 135.467 33.6 166.208q0 88.352-33.6 166.048t-91.2 135.52-135.467 91.563q-77.867 33.728-166.208 33.728zM512 867.552q148.885 0 252.224-103.819 103.328-103.819 103.328-251.733 0-5.333-0.171-10.133-0.181-4.8-0.181-8.715-6.048 28.8-29.088 48t-54.464 19.2h-85.333q-35.2 0-60.267-25.067t-25.067-60.267v-42.667h-170.667v-85.333q0-35.2 25.067-60.267t60.267-25.067h42.667v-15.637q0-19.563 14.037-42.848 14.048-23.285 32.533-30.752-24.885-7.467-50.912-11.733-26.037-4.267-53.973-4.267-147.915 0-251.733 103.328-103.819 103.339-103.819 252.224h177.771q70.4 0 120.533 50.133t50.133 120.533v42.667h-128v113.781q31.296 13.867 65.035 21.152t70.080 7.285z"
          ],
          "attrs": [
            {}
          ],
          "isMulticolor": false,
          "isMulticolor2": false,
          "grid": 32,
          "tags": [
            "globe"
          ]
        },
        {
          "id": 15,
          "paths": [
            "M512 872.181q-12.587 0-25.621-4.533t-22.923-14.496l-62.037-57.067q-125.867-116.267-220.971-224.533-95.115-108.267-95.115-230.219 0-97.536 65.419-162.901 65.429-65.365 162.133-65.365 55.115 0 107.381 25.419 52.267 25.429 91.733 79.115 43.019-53.685 93.152-79.115 50.133-25.419 105.963-25.419 96.704 0 162.133 65.365 65.419 65.365 65.419 162.901 0 121.952-94.933 230.4t-221.515 224.715l-61.867 56.885q-9.771 9.867-22.667 14.357-12.885 4.491-25.685 4.491zM480 292.981q-29.515-49.429-72.533-79.115t-94.581-29.685q-68.267 0-112.352 44.437-44.085 44.448-44.085 113.024 0 59.424 40.8 125.493 40.8 66.059 97.6 128.171t117.419 115.808q60.619 53.685 99.733 89.6 39.115-35.2 99.733-89.248t117.333-116.619q56.715-62.581 97.6-128.672t40.885-124.843q0-68.267-44.437-112.715-44.448-44.437-112-44.437-52.267 0-94.933 29.333t-73.6 79.467q-6.048 9.237-13.867 13.504-7.829 4.267-17.429 4.267t-17.771-4.267q-8.181-4.267-13.515-13.504z"
          ],
          "attrs": [
            {}
          ],
          "isMulticolor": false,
          "isMulticolor2": false,
          "grid": 32,
          "tags": [
            "heart",
            "favorite"
          ]
        },
        {
          "id": 24,
          "paths": [
            "M156.448 362.667q0 34.133 11.904 65.419 11.915 31.296 42.848 72.363t84.619 98.304q53.696 57.248 137.248 142.581 4.267 4.267 9.067 2.667t5.867-6.933l27.381-239.285h-10.667q-48.363 0-80.715-35.029-32.352-35.019-15.285-94.4l41.952-144.704q-21.333-10.667-43.915-17.6-22.571-6.933-46.752-6.933-67.755 0-115.659 47.893-47.893 47.904-47.893 115.659zM867.552 362.667q0-67.755-47.893-115.659-47.904-47.893-115.659-47.893-14.816 0-29.632 2.667t-28.683 7.637l-34.133 103.467h3.563q45.152 4.267 70.933 42.133 25.771 37.867 9.419 92.267l-69.685 238.581q-2.133 5.333 3.733 9.067t11.2-1.6q69.333-68.267 113.419-116.085 44.085-47.829 69.515-84.981 25.419-37.152 34.667-67.381 9.237-30.219 9.237-62.219zM513.067 889.6q-13.515 0-26.133-5.333t-22.219-14.581q-119.829-114.485-194.133-190.752-74.315-76.267-115.381-131.2t-55.467-96.885q-14.4-41.963-14.4-88.181 0-98.133 68.267-166.4t166.4-68.267q70.4 0 124.8 24t39.467 75.2l-44.448 154.315q-5.333 17.067 5.515 31.104 10.848 14.048 28.619 14.048h81.429l-34.133 296.939q-1.067 8.843 6.933 9.909t10.133-6.4l89.6-296.896q5.685-17.067-5.173-31.637-10.859-14.581-28.96-14.581h-81.781l66.485-198.752q11.733-35.915 48.608-46.581t76.907-10.667q98.133 0 166.4 68.267t68.267 166.4q0 45.515-15.285 88.533-15.296 43.019-56.715 98.848-41.419 55.819-114.848 131.733-73.419 75.904-190.037 187.904-9.6 9.248-22.4 14.581t-26.315 5.333z"
          ],
          "attrs": [
            {}
          ],
          "isMulticolor": false,
          "isMulticolor2": false,
          "grid": 32,
          "tags": [
            "heart_broken",
            "heart",
            "broken",
            "crack"
          ]
        },
        {
          "id": 18,
          "paths": [
            "M355.552 747.733l156.448-93.867 156.448 94.933-41.6-177.781 137.6-119.467-181.333-16-71.115-167.819-71.115 166.752-181.333 16 137.6 119.829-41.6 177.419zM512 737.067l-191.285 115.2q-9.6 6.048-20.267 5.333t-18.848-6.752q-8.181-6.048-12.448-15.467-4.267-9.429-1.771-21.163l50.485-217.952-168.885-146.848q-9.248-8.171-11.2-18.304-1.963-10.133 0.885-19.733t10.667-16 19.915-7.829l223.285-19.552 86.4-205.515q4.619-10.667 14.048-16 9.419-5.333 19.019-5.333t19.019 5.333q9.429 5.333 14.048 16l86.4 205.515 223.285 19.552q12.096 1.429 19.915 7.829t10.667 16 0.885 19.733q-1.952 10.133-11.2 18.304l-168.885 146.848 50.485 217.952q2.496 11.733-1.771 21.163-4.267 9.419-12.448 15.467-8.181 6.037-18.848 6.752t-20.267-5.333l-191.285-115.2z"
          ],
          "attrs": [
            {}
          ],
          "isMulticolor": false,
          "isMulticolor2": false,
          "grid": 32,
          "tags": [
            "star"
          ]
        },
        {
          "id": 21,
          "paths": [
            "M308.619 484.267q17.781-35.552 37.696-69.685 19.904-34.133 42.667-66.133l-76.096-15.296-107.371 107.381 103.104 43.733zM846.219 164.619q-97.419 4.267-184 45.515-86.571 41.248-165.152 119.819-36.981 36.981-72.181 89.6-35.2 52.629-59.371 108.096l135.104 134.752q55.467-24.181 108.096-59.381 52.619-35.2 89.6-72.171 78.571-78.581 119.819-164.629 41.248-86.037 45.515-183.467 0-3.552-1.248-7.104-1.248-3.563-3.733-6.048t-5.685-3.733-6.763-1.248zM599.467 429.152q-22.4-22.4-22.4-55.285t22.4-55.285 55.467-22.4 55.467 22.4 22.4 55.285-22.4 55.285-55.467 22.4-55.467-22.4zM544 720l43.733 102.752 107.381-107.371-14.581-76.096q-32 22.763-66.485 42.848-34.496 20.085-70.048 37.867zM934.048 132.619q4.971 128-41.6 240.181-46.581 112.181-147.2 212.8-0.715 0.715-1.429 1.067-0.704 0.352-1.419 1.067l22.752 113.419q3.563 17.781-1.419 34.496-4.981 16.704-17.781 29.504l-145.067 145.067q-13.152 13.163-31.637 9.781-18.496-3.381-25.6-21.152l-70.048-162.496-180.981-181.685-163.2-69.333q-17.771-7.115-20.971-25.952-3.2-18.848 9.952-32l144.352-144.363q12.8-12.8 29.696-18.133 16.885-5.333 34.667-1.771l113.419 22.752q0.715-0.715 1.419-1.067 0.715-0.352 1.429-1.067 100.619-100.619 212.437-147.2 111.829-46.581 239.829-41.6 7.104 0.352 13.867 3.381 6.752 3.019 12.437 8.704 5.696 5.696 8.715 12.096t3.381 13.504zM161.781 678.752q37.333-37.333 91.2-37.867t91.2 36.8 36.8 91.2-37.867 91.2q-50.496 50.496-120.363 60.448t-140.267 19.552q9.6-70.4 19.2-140.619t60.096-120.715zM211.915 729.248q-23.115 24.533-30.4 57.237-7.296 32.715-12.981 66.496 33.781-5.696 66.485-12.8 32.715-7.115 57.248-30.229 18.485-16.352 18.848-40.533 0.352-24.171-16.715-41.952-17.781-17.067-41.952-16.885-24.181 0.171-40.533 18.667z"
          ],
          "attrs": [
            {}
          ],
          "isMulticolor": false,
          "isMulticolor2": false,
          "grid": 32,
          "tags": [
            "rocket",
            "launch"
          ]
        },
        {
          "id": 28,
          "paths": [
            "M156.448 853.333q-28.8 0-49.963-21.152-21.152-21.163-21.152-49.963v-540.437q0-28.8 21.152-49.963 21.163-21.152 49.963-21.152h711.104q28.8 0 49.963 21.152 21.152 21.163 21.152 49.963v540.437q0 28.8-21.152 49.963-21.163 21.152-49.963 21.152h-711.104zM156.448 782.219h711.104v-452.267h-711.104v452.267zM380.085 556.085l-86.037-86.037q-10.667-10.667-10.133-24.896 0.533-14.219 11.2-24.885 10.667-10.315 24.885-10.485 14.219-0.181 24.885 10.485l110.933 110.933q10.667 10.667 10.667 24.885 0 14.229-10.667 24.896l-110.933 110.933q-10.304 10.304-24.704 10.485t-25.067-10.485q-10.315-10.315-10.315-24.896 0-14.571 10.315-24.885l84.971-86.048zM554.667 719.648q-15.285 0-25.419-10.133t-10.133-25.429q0-15.285 10.133-25.419t25.419-10.133h170.667q15.285 0 25.419 10.133t10.133 25.419q0 15.296-10.133 25.429t-25.419 10.133h-170.667z"
          ],
          "attrs": [
            {}
          ],
          "isMulticolor": false,
          "isMulticolor2": false,
          "grid": 32,
          "tags": [
            "terminal",
            "prompt"
          ]
        },
        {
          "id": 23,
          "paths": [
            "M640 853.333q-142.933 0-242.133-99.2t-99.2-242.133q0-142.581 99.2-241.952 99.2-99.381 242.133-99.381 142.581 0 241.952 99.381 99.381 99.371 99.381 241.952 0 142.933-99.381 242.133-99.371 99.2-241.952 99.2zM639.829 782.219q112.523 0 191.456-78.763t78.933-191.285-78.763-191.456-191.285-78.933-191.456 78.763-78.933 191.285 78.763 191.456 191.285 78.933zM675.552 497.067v-120.181q0-14.571-10.219-25.067-10.219-10.485-25.333-10.485t-25.333 10.133-10.219 25.419v135.467q0 6.805 2.667 13.184t8 11.712l104.885 104.171q10.528 10.667 24.992 10.667 14.475 0 25.141-10.549 10.667-10.56 10.667-25.067 0-14.517-10.667-25.184l-94.581-94.219zM120.885 376.885q-15.104 0-25.333-10.251-10.219-10.261-10.219-25.429 0-15.157 10.219-25.291 10.229-10.133 25.333-10.133h99.563q15.104 0 25.333 10.251 10.219 10.261 10.219 25.429 0 15.157-10.219 25.291-10.229 10.133-25.333 10.133h-99.563zM78.219 547.552q-15.104 0-25.333-10.251-10.219-10.261-10.219-25.429 0-15.157 10.219-25.291 10.229-10.133 25.333-10.133h142.229q15.104 0 25.333 10.251 10.219 10.261 10.219 25.429 0 15.157-10.219 25.291-10.229 10.133-25.333 10.133h-142.229zM120.885 718.219q-15.104 0-25.333-10.251-10.219-10.261-10.219-25.429 0-15.157 10.219-25.291 10.229-10.133 25.333-10.133h99.563q15.104 0 25.333 10.251 10.219 10.261 10.219 25.429 0 15.157-10.219 25.291-10.229 10.133-25.333 10.133h-99.563z"
          ],
          "attrs": [
            {}
          ],
          "isMulticolor": false,
          "isMulticolor2": false,
          "grid": 32,
          "tags": [
            "acute",
            "urgent",
            "timely"
          ]
        },
        {
          "id": 25,
          "paths": [
            "M509.867 896q-145.781 0-252.448-95.115-106.667-95.104-124.8-236.971-2.133-13.867 7.467-24.715t24.896-11.552q14.219-0.715 24.885 8.171 10.667 8.896 13.867 23.829 16.352 113.771 102.752 189.504t203.381 75.733q131.915 0 223.467-92.267t91.552-224.171q0-129.781-92.267-219.563-92.267-89.771-222.752-89.771-72.885 0-136.533 33.419t-109.515 89.6h78.229q15.285 0 25.419 10.133t10.133 25.419q0 15.296-10.133 25.429t-25.419 10.133h-162.848q-15.285 0-25.419-10.133t-10.133-25.429v-162.133q0-15.285 10.133-25.419t25.419-10.133 25.419 10.133 10.133 25.419v73.248q55.115-66.133 132.096-103.467 76.971-37.333 163.019-37.333 80 0 150.219 30.048 70.229 30.037 122.667 81.771 52.448 51.733 82.848 121.248t30.4 149.515-30.4 150.219-82.848 122.315q-52.437 52.085-122.667 82.485-70.219 30.4-150.219 30.4zM548.267 496.352l117.333 115.915q10.315 10.315 10.315 25.248t-10.315 25.237q-10.315 10.315-24.885 10.315-14.581 0-24.896-10.315l-128-126.571q-5.685-5.696-8.171-12.267-2.496-6.581-2.496-13.696v-178.133q0-15.285 10.133-25.419t25.429-10.133q15.285 0 25.419 10.133t10.133 25.419v164.267z"
          ],
          "attrs": [
            {}
          ],
          "isMulticolor": false,
          "isMulticolor2": false,
          "grid": 32,
          "tags": [
            "history"
          ]
        },
        {
          "id": 22,
          "paths": [
            "M156.448 512.352q0 104.896 55.637 191.296 55.648 86.4 149.867 130.485 13.515 6.752 19.381 20.448 5.867 13.685-1.248 26.485-8.533 13.867-23.637 17.952-15.115 4.096-30.4-3.019-111.296-53.333-176-156.8-64.715-103.467-64.715-226.848 0-32 4.8-64t14.752-62.933l-33.067 19.2q-12.8 7.467-26.667 4.096-13.867-3.381-20.971-16.181-7.115-12.8-3.381-27.2t16.533-21.515l129.067-74.667q12.8-7.104 27.2-3.371t21.515 16.533l74.667 128q7.104 12.8 3.371 27.2t-16.533 21.504q-12.8 7.115-27.2 3.381t-21.504-16.533l-42.667-72.885q-13.867 33.419-21.333 68.267-7.467 34.837-7.467 71.104zM512 156.448q-55.115 0-106.667 16.533t-96.352 48.533q-13.163 8.533-27.915 7.285t-21.867-14.048q-8.181-14.219-4.267-30.037 3.915-15.829 17.419-24.715 52.981-36.267 113.963-55.467 60.971-19.2 125.685-19.2 89.952 0 171.2 35.733t142.048 101.867v-38.048q0-15.285 10.133-25.419t25.419-10.133 25.419 10.133 10.133 25.419v149.333q0 15.296-10.133 25.429t-25.419 10.133h-149.333q-15.285 0-25.419-10.133t-10.133-25.429q0-15.285 10.133-25.419t25.419-10.133h84.981q-50.496-67.2-125.163-104.715-74.667-37.504-159.285-37.504zM777.248 749.867q49.771-56.181 72.533-126.219 22.752-70.048 14.933-144-1.429-15.296 8-27.029 9.419-11.733 24-11.733 16 0 27.2 12.096 11.2 12.085 12.619 28.8 5.685 80.704-17.248 156.619t-73.067 139.2q-45.152 56.885-105.419 95.285t-131.019 54.763l30.571 17.771q12.8 7.115 16 21.515t-3.904 27.2q-7.115 12.8-20.981 16t-26.667-3.915l-130.133-74.667q-12.8-7.104-16.533-21.504t3.381-27.2l74.667-128.363q7.104-12.8 21.333-16.352 14.219-3.552 27.019 3.552 12.8 7.115 16.181 21.163 3.371 14.037-3.733 26.837l-43.733 76.448q65.067-7.115 122.837-37.152 57.781-30.048 101.163-79.115z"
          ],
          "attrs": [
            {}
          ],
          "isMulticolor": false,
          "isMulticolor2": false,
          "grid": 32,
          "tags": [
            "cycle",
            "loop"
          ]
        },
        {
          "id": 20,
          "paths": [
            "M285.152 896q-29.333 0-50.219-20.885-20.885-20.896-20.885-50.229v-590.219h-7.829q-15.104 0-25.333-10.261-10.219-10.251-10.219-25.419t10.219-25.301q10.229-10.133 25.333-10.133h169.248q0-15.285 10.219-25.419 10.229-10.133 25.333-10.133h201.963q15.104 0 25.333 10.219 10.219 10.229 10.219 25.333h169.248q15.104 0 25.333 10.261 10.219 10.261 10.219 25.419 0 15.168-10.219 25.301-10.229 10.133-25.333 10.133h-7.829v590.219q0 29.333-20.885 50.229-20.885 20.885-50.219 20.885h-453.696zM738.848 234.667h-453.696v590.219h453.696v-590.219zM424.661 735.285q15.157 0 25.291-10.219t10.133-25.333v-340.619q0-15.115-10.251-25.333-10.261-10.229-25.429-10.229-15.157 0-25.291 10.229-10.133 10.219-10.133 25.333v340.619q0 15.115 10.251 25.333 10.261 10.219 25.429 10.219zM599.595 735.285q15.157 0 25.291-10.219t10.133-25.333v-340.619q0-15.115-10.251-25.333-10.261-10.229-25.429-10.229-15.157 0-25.291 10.229-10.133 10.219-10.133 25.333v340.619q0 15.115 10.251 25.333 10.261 10.219 25.429 10.219zM285.152 234.667v0z"
          ],
          "attrs": [
            {}
          ],
          "isMulticolor": false,
          "isMulticolor2": false,
          "grid": 32,
          "tags": [
            "delete",
            "trash",
            "bin"
          ]
        },
        {
          "id": 17,
          "paths": [
            "M512 561.781l-219.019 219.019q-10.315 10.315-24.896 10.315-14.571 0-24.885-10.315t-10.315-24.885q0-14.581 10.315-24.896l219.019-219.019-219.019-219.019q-10.315-10.315-10.315-24.896 0-14.571 10.315-24.885t24.885-10.315q14.581 0 24.896 10.315l219.019 219.019 219.019-219.019q10.315-10.315 24.896-10.315 14.571 0 24.885 10.315t10.315 24.885q0 14.581-10.315 24.896l-219.019 219.019 219.019 219.019q10.315 10.315 10.315 24.896 0 14.571-10.315 24.885t-24.885 10.315q-14.581 0-24.896-10.315l-219.019-219.019z"
          ],
          "attrs": [
            {}
          ],
          "isMulticolor": false,
          "isMulticolor2": false,
          "grid": 32,
          "tags": [
            "close",
            "cross",
            "x"
          ]
        }
      ],
      "invisible": false,
      "colorThemes": []
    },
    {
      "selection": [
        {
          "order": 1,
          "id": 1,
          "name": "github",
          "prevSize": 32,
          "code": 59678,
          "tempChar": "",
          "ligatures": "github"
        },
        {
          "order": 1,
          "id": 0,
          "name": "matrix",
          "prevSize": 32,
          "code": 59679,
          "tempChar": "",
          "ligatures": "matrix"
        },
        {
          "order": 31,
          "id": 2,
          "name": "discord",
          "prevSize": 32,
          "code": 59680,
          "tempChar": "",
          "ligatures": "discord"
        }
      ],
      "id": 5,
      "metadata": {
        "name": "Brands (subset)",
        "importSize": {
          "width": 32,
          "height": 32
        },
        "url": "https://simpleicons.org",
        "designer": "N/A",
        "license": "CC0 1.0 Universal",
        "licenseURL": "https://github.com/simple-icons/simple-icons/blob/develop/LICENSE.md",
        "iconsHash": 1591697341
      },
      "height": 1024,
      "prevSize": 32,
      "icons": [
        {
          "id": 1,
          "paths": [
            "M512 12.672c-282.88 0-512 229.248-512 512 0 226.261 146.688 418.133 350.080 485.76 25.6 4.821 34.987-11.008 34.987-24.619 0-12.16-0.427-44.373-0.64-87.040-142.421 30.891-172.459-68.693-172.459-68.693-23.296-59.093-56.96-74.88-56.96-74.88-46.379-31.744 3.584-31.104 3.584-31.104 51.413 3.584 78.421 52.736 78.421 52.736 45.653 78.293 119.851 55.68 149.12 42.581 4.608-33.109 17.792-55.68 32.427-68.48-113.707-12.8-233.216-56.832-233.216-253.013 0-55.893 19.84-101.547 52.693-137.387-5.76-12.928-23.040-64.981 4.48-135.509 0 0 42.88-13.739 140.8 52.48 40.96-11.392 84.48-17.024 128-17.28 43.52 0.256 87.040 5.888 128 17.28 97.28-66.219 140.16-52.48 140.16-52.48 27.52 70.528 10.24 122.581 5.12 135.509 32.64 35.84 52.48 81.493 52.48 137.387 0 196.693-119.68 240-233.6 252.587 17.92 15.36 34.56 46.763 34.56 94.72 0 68.523-0.64 123.563-0.64 140.203 0 13.44 8.96 29.44 35.2 24.32 204.843-67.157 351.403-259.157 351.403-485.077 0-282.752-229.248-512-512-512z"
          ],
          "attrs": [
            {}
          ],
          "isMulticolor": false,
          "isMulticolor2": false,
          "tags": [
            "github",
            "company"
          ],
          "grid": 0
        },
        {
          "id": 0,
          "paths": [
            "M26.965 23.467v977.067h70.315v23.467h-97.28v-1024h97.28v23.467zM327.467 333.227v49.365h1.408c13.184-18.901 29.141-33.451 47.659-43.691 18.475-10.453 39.936-15.573 64-15.573 23.040 0 44.075 4.565 63.189 13.397 19.115 8.875 33.493 24.832 43.52 47.275 10.837-15.957 25.6-30.123 44.117-42.325 18.517-12.245 40.533-18.347 65.963-18.347 19.328 0 37.205 2.389 53.76 7.125 16.555 4.693 30.549 12.203 42.368 22.613 11.776 10.453 20.864 23.851 27.563 40.576 6.485 16.725 9.813 36.821 9.813 60.459v244.395h-100.224v-206.976c0-12.203-0.427-23.851-1.365-34.645-0.749-10.384-3.503-19.965-7.876-28.587l0.196 0.427c-4.344-8.093-10.718-14.604-18.454-18.993l-0.234-0.122c-8.277-4.693-19.499-7.083-33.493-7.083-14.165 0-25.6 2.731-34.261 8.064-8.55 5.315-15.469 12.494-20.328 21.002l-0.152 0.289c-4.886 8.571-8.361 18.597-9.808 29.267l-0.048 0.429c-1.565 10.018-2.494 21.619-2.56 33.424v203.505h-100.267v-204.8c0-10.837-0.171-21.461-0.768-32.085-0.381-10.656-2.586-20.69-6.313-29.95l0.211 0.595c-3.602-8.998-9.741-16.347-17.529-21.354l-0.178-0.107c-8.277-5.333-20.309-8.107-36.437-8.107-4.736 0-11.051 1.024-18.731 3.157-7.68 2.176-15.36 6.101-22.613 12.032-7.296 5.888-13.611 14.379-18.731 25.387-5.12 11.051-7.68 25.6-7.68 43.52v211.883h-100.224v-365.44zM997.035 1000.533v-977.067h-70.315v-23.467h97.28v1024h-97.28v-23.467z"
          ],
          "attrs": [
            {}
          ],
          "isMulticolor": false,
          "isMulticolor2": false,
          "tags": [
            "matrix",
            "company"
          ],
          "grid": 0
        },
        {
          "id": 2,
          "paths": [
            "M862.805 0c59.989 0 108.373 48.512 111.232 105.6v918.4l-114.219-96.981-62.72-57.088-68.437-59.648 28.587 94.080h-598.955c-59.819 0-108.373-45.44-108.373-105.643v-692.907c0-57.088 48.64-105.685 108.587-105.685h704zM601.771 242.475h-1.28l-8.619 8.533c88.448 25.6 131.243 65.579 131.243 65.579-57.003-28.501-108.373-42.752-159.744-48.512-37.12-5.76-74.24-2.731-105.6 0h-8.533c-20.053 0-62.72 8.533-119.893 31.36-19.925 8.661-31.36 14.336-31.36 14.336s42.752-42.752 136.96-65.579l-5.76-5.76c0 0-71.339-2.731-148.352 54.187 0 0-77.013 134.144-77.013 299.52 0 0 42.667 74.24 159.701 77.056 0 0 17.067-22.741 34.347-42.752-65.707-19.968-91.307-59.904-91.307-59.904s5.717 2.816 14.293 8.533h2.56c1.28 0 1.877 0.64 2.56 1.28v0.256c0.683 0.683 1.28 1.28 2.56 1.28 14.080 5.803 28.16 11.52 39.68 17.067 19.883 8.619 45.44 17.195 76.8 22.869 39.68 5.76 85.163 8.533 136.96 0 25.6-5.76 51.2-11.392 76.8-22.827 16.64-8.533 37.12-17.067 59.605-31.445 0 0-25.6 39.936-94.080 59.904 14.080 19.883 33.92 42.667 33.92 42.667 117.077-2.56 162.56-76.8 165.12-73.643 0-165.12-77.44-299.52-77.44-299.52-69.76-51.797-135.040-53.76-146.56-53.76zM608.939 430.763c29.995 0 54.187 25.6 54.187 56.96 0 31.573-24.32 57.173-54.187 57.173s-54.187-25.6-54.187-56.917c0.085-31.573 24.448-57.088 54.187-57.216zM415.104 430.763c29.867 0 54.016 25.6 54.016 56.96 0 31.573-24.32 57.173-54.187 57.173s-54.187-25.6-54.187-56.917c0-31.573 24.32-57.088 54.357-57.216z"
          ],
          "attrs": [],
          "isMulticolor": false,
          "isMulticolor2": false,
          "tags": [
            "discord",
            "company"
          ],
          "grid": 0,
          "colorPermutations": {}
        }
      ],
      "invisible": false,
      "colorThemes": []
    }
  ],
  "preferences": {
    "showGlyphs": true,
    "showQuickUse": true,
    "showQuickUse2": true,
    "showSVGs": true,
    "fontPref": {
      "prefix": "icon-",
      "metadata": {
        "fontFamily": "phicons",
        "majorVersion": 1,
        "minorVersion": 0
      },
      "metrics": {
        "emSize": 1024,
        "baseline": 6.25,
        "whitespace": 50
      },
      "embed": false,
      "resetPoint": 59648,
      "autoHost": false,
      "showSelector": false,
      "includeMetadata": false,
      "showMetrics": true,
      "showMetadata": true,
      "showVersion": true,
      "cssVars": true,
      "cssVarsFormat": "scss"
    },
    "imagePref": {
      "prefix": "icon-",
      "png": true,
      "useClassSelector": true,
      "color": 0,
      "bgColor": 16777215,
      "classSelector": ".icon",
      "name": "icomoon"
    },
    "historySize": 50,
    "showCodes": true,
    "gridSize": 16,
    "showLiga": true,
    "showGrid": true,
    "quickUsageToken": {
      "phischdev": "ZjUwZjY0MWY2MiMxNzE1Nzg3MzUxI0FrTEFreVRwY0kwSTJSaWZuN0RkZXJsMkZhTlI4TC9mUWRDQyt5MFhRZXRS"
    }
  },
  "uid": -1
}